{
  "title": "2026 Football Coaches - Ole Miss Athletics - Hotty Toddy",
  "url": "https://olemisssports.com/sports/football/coaches",
  "status_code": 200,
  "chars": 16732,
  "links_count": 271,
  "scraped_at": "2026-04-09T15:01:59.861798+00:00",
  "content_hash": "9eb33a9c9c88e92d",
  "file": "C:\\Users\\rishj\\foai\\smelter-os\\sqwaadrun\\data\\college-football\\coaches-contacts\\ole-miss-coaching-staff.md",
  "social_media": [
    {
      "platform": "twitter",
      "handle": "@OleMissBSB",
      "url": "https://x.com/OleMissBSB"
    },
    {
      "platform": "instagram",
      "handle": "@olemissbsb",
      "url": "https://instagram.com/olemissbsb"
    },
    {
      "platform": "twitter",
      "handle": "@OleMissMBB",
      "url": "https://x.com/OleMissMBB"
    },
    {
      "platform": "instagram",
      "handle": "@olemissmbb",
      "url": "https://instagram.com/olemissmbb"
    },
    {
      "platform": "twitter",
      "handle": "@OleMissTrack",
      "url": "https://x.com/OleMissTrack"
    },
    {
      "platform": "instagram",
      "handle": "@olemisstrack",
      "url": "https://instagram.com/olemisstrack"
    },
    {
      "platform": "twitter",
      "handle": "@OleMissFB",
      "url": "https://x.com/OleMissFB"
    },
    {
      "platform": "instagram",
      "handle": "@olemissfb",
      "url": "https://instagram.com/olemissfb"
    },
    {
      "platform": "twitter",
      "handle": "@OleMissMGolf",
      "url": "https://x.com/OleMissMGolf"
    },
    {
      "platform": "instagram",
      "handle": "@olemissmgolf",
      "url": "https://instagram.com/olemissmgolf"
    },
    {
      "platform": "twitter",
      "handle": "@OleMissMTennis",
      "url": "https://x.com/OleMissMTennis"
    },
    {
      "platform": "instagram",
      "handle": "@olemissmtennis",
      "url": "https://instagram.com/olemissmtennis"
    },
    {
      "platform": "twitter",
      "handle": "@OleMissWBB",
      "url": "https://x.com/OleMissWBB"
    },
    {
      "platform": "instagram",
      "handle": "@olemisswbb",
      "url": "https://instagram.com/olemisswbb"
    },
    {
      "platform": "twitter",
      "handle": "@OleMissWGolf",
      "url": "https://x.com/OleMissWGolf"
    },
    {
      "platform": "instagram",
      "handle": "@olemisswgolf",
      "url": "https://instagram.com/olemisswgolf"
    },
    {
      "platform": "twitter",
      "handle": "@OleMissRifle",
      "url": "https://x.com/OleMissRifle"
    },
    {
      "platform": "instagram",
      "handle": "@OleMissRifle",
      "url": "https://instagram.com/OleMissRifle"
    },
    {
      "platform": "twitter",
      "handle": "@OleMissSoccer",
      "url": "https://x.com/OleMissSoccer"
    },
    {
      "platform": "instagram",
      "handle": "@OfficialOleMissSoccer",
      "url": "https://instagram.com/OfficialOleMissSoccer"
    },
    {
      "platform": "twitter",
      "handle": "@OleMissSoftball",
      "url": "https://x.com/OleMissSoftball"
    },
    {
      "platform": "instagram",
      "handle": "@olemisssoftball",
      "url": "https://instagram.com/olemisssoftball"
    },
    {
      "platform": "twitter",
      "handle": "@OleMissWTennis",
      "url": "https://x.com/OleMissWTennis"
    },
    {
      "platform": "instagram",
      "handle": "@OleMissWTennis",
      "url": "https://instagram.com/OleMissWTennis"
    },
    {
      "platform": "twitter",
      "handle": "@olemissvb",
      "url": "https://x.com/olemissvb"
    },
    {
      "platform": "instagram",
      "handle": "@OleMissVB",
      "url": "https://instagram.com/OleMissVB"
    }
  ],
  "emails": [
    "jjsingle@olemiss.edu",
    "wamcdowe@olemiss.edu",
    "ksugarm@olemiss.edu",
    "mtmazur@olemiss.edu",
    "fwilson2@olemiss.edu",
    "jschoudh@olemiss.edu",
    "zwithers@olemiss.edu",
    "rcooley1@olemiss.edu",
    "fbadkins@olemiss.edu",
    "smhamilt@olemiss.edu",
    "pathoma3@olemiss.edu",
    "weyerty@olemiss.edu",
    "megan@olemiss.edu",
    "dxayala@olemiss.edu",
    "kaherman@olemiss.edu",
    "mcspurlo@olemiss.edu",
    "bbboyd@olemiss.edu",
    "adcromer@olemiss.edu",
    "pcarter1@olemiss.edu",
    "jdhess@olemiss.edu",
    "mgebert@olemiss.edu",
    "srmcknig@olemiss.edu",
    "dewilso2@olemiss.edu",
    "swynn@olemiss.edu",
    "cabryan5@olemiss.edu",
    "cmjames4@olemiss.edu",
    "mesieber@olemiss.edu",
    "jfray@olemiss.edu",
    "kmmurph3@olemiss.edu",
    "jftucker@olemiss.edu",
    "pconstan@olemiss.edu",
    "wrday1@olemiss.edu",
    "ljmckee@olemiss.edu",
    "kmdesteu@olemiss.edu",
    "kckeys@olemiss.edu",
    "lpmarijn@olemiss.edu",
    "ckcrain@olemiss.edu",
    "aauer@olemiss.edu",
    "kdbolde1@olemiss.edu",
    "mclapp@olemiss.edu",
    "tluke@olemiss.edu",
    "matthewe@olemiss.edu",
    "mamorri6@olemiss.edu",
    "rkambros@olemiss.edu",
    "drmoncri@olemiss.edu",
    "kkelly6@olemiss.edu",
    "jernigan@olemiss.edu",
    "btturnag@olemiss.edu",
    "bssparkm@olemiss.edu",
    "rebelfootball@olemiss.edu",
    "atlagro1@olemiss.edu",
    "malittl4@olemiss.edu",
    "cnichol6@olemiss.edu",
    "agokeefe@olemiss.edu",
    "jreiling@olemiss.edu"
  ],
  "phones": [
    "662-915-1594",
    "662-915-1841",
    "662-915-7890",
    "662-915-1935",
    "662-915-1564",
    "662-832-5394"
  ]
}